petalouda/__init__.py
petalouda-0.0.0.dist-info/LICENSE
petalouda-0.0.0.dist-info/METADATA
petalouda-0.0.0.dist-info/WHEEL
petalouda-0.0.0.dist-info/top_level.txt
petalouda-0.0.0.dist-info/RECORD
